oanda_sdk/__init__.py
oanda_sdk/account.py
oanda_sdk/client.py
oanda_sdk/instrument.py
oanda_sdk/order.py
oanda_sdk/position.py
oanda_sdk/trade.py
oanda_sdk/transaction.py
oanda_sdk-1.0.3.dist-info/METADATA
oanda_sdk-1.0.3.dist-info/WHEEL
oanda_sdk-1.0.3.dist-info/licenses/LICENSE
oanda_sdk-1.0.3.dist-info/RECORD
