Metadata-Version: 2.1
Name: oanda_sdk
Version: 1.0.3
Summary: An SDK for trading forex currency pairs.
Project-URL: Homepage, https://nat-leo.github.io/oanda-sdk/
Author-email: Nat Liu <n8wyliu@gmail.com>
License-File: LICENSE
Classifier: License :: OSI Approved :: MIT License
Classifier: Operating System :: OS Independent
Classifier: Programming Language :: Python :: 3
Requires-Python: >=3.7
